meteor/__init__.py
meteor/counter.py
meteor/data/category_pcm.feather
meteor/data/ko_list_v116.feather
meteor/data/modules_definition.feather
meteor/data/zenodo.json
meteor/downloader.py
meteor/fastqimporter.py
meteor/mapper.py
meteor/merging.py
meteor/meteor.py
meteor/parser.py
meteor/phylogeny.py
meteor/profiler.py
meteor/referencebuilder.py
meteor/session.py
meteor/strain.py
meteor/tests/__init__.py
meteor/tests/conftest.py
meteor/tests/test_counter/catalogue/mock/database/mock_annotation.tsv
meteor/tests/test_counter/catalogue/mock/database/mock_msp.tsv
meteor/tests/test_counter/catalogue/mock/fasta/mock.1.bt2
meteor/tests/test_counter/catalogue/mock/fasta/mock.2.bt2
meteor/tests/test_counter/catalogue/mock/fasta/mock.3.bt2
meteor/tests/test_counter/catalogue/mock/fasta/mock.4.bt2
meteor/tests/test_counter/catalogue/mock/fasta/mock.fasta.gz
meteor/tests/test_counter/catalogue/mock/fasta/mock.rev.1.bt2
meteor/tests/test_counter/catalogue/mock/fasta/mock.rev.2.bt2
meteor/tests/test_counter/catalogue/mock/mock_reference.json
meteor/tests/test_counter/expected_output/count.tsv.xz
meteor/tests/test_counter/part1/part1.fastq.gz
meteor/tests/test_counter/part1/part1_census_stage_0.json
meteor/tests/test_counter/test/part2/part2.tsv
meteor/tests/test_counter/test/part2/part2_census_stage_1.json
meteor/tests/test_counter/total_raw.cram
meteor/tests/test_counter/total_raw.cram.crai
meteor/tests/test_counter.py
meteor/tests/test_downloader/test.tar.xz
meteor/tests/test_downloader.py
meteor/tests/test_fastq_importer/paired/test2_1.fastq.gz
meteor/tests/test_fastq_importer/paired/test2_2.fastq.gz
meteor/tests/test_fastq_importer/paired/test3_1.fq
meteor/tests/test_fastq_importer/paired/test3_2.fq
meteor/tests/test_fastq_importer/paired/test_R1.fastq.gz
meteor/tests/test_fastq_importer/paired/test_R2.fastq.gz
meteor/tests/test_fastq_importer/paired_mask/test2_Zymo_6400_1.fq.gz
meteor/tests/test_fastq_importer/paired_mask/test2_Zymo_6400_2.fq.gz
meteor-2.0.22.dist-info/METADATA
meteor-2.0.22.dist-info/WHEEL
meteor-2.0.22.dist-info/entry_points.txt
meteor-2.0.22.dist-info/licenses/COPYING
meteor-2.0.22.dist-info/RECORD
