Metadata-Version: 2.4
Name: meteor
Version: 2.0.22
Summary: Meteor - A plateform for quantitative metagenomic profiling of complex ecosystems
License: GPL-3.0-or-later
License-File: COPYING
Keywords: Metagenomics
Author: Amine Ghozlane
Author-email: amine.ghozlane@pasteur.fr
Requires-Python: >=3.11,<3.14
Classifier: Environment :: Console
Classifier: Intended Audience :: Science/Research
Classifier: License :: OSI Approved :: GNU General Public License v3 or later (GPLv3+)
Classifier: Operating System :: OS Independent
Classifier: Programming Language :: Python :: 3
Classifier: Programming Language :: Python :: 3.11
Classifier: Programming Language :: Python :: 3.12
Classifier: Programming Language :: Python :: 3.13
Classifier: Topic :: Scientific/Engineering :: Bio-Informatics
Requires-Dist: bgzip (>=0.5.1,<0.6.0)
Requires-Dist: biom-format (>=2.1.15,<3.0.0)
Requires-Dist: cogent3 (>=2025.9.8a8,<2026.0.0)
Requires-Dist: ete4 (>=4.4.0,<5.0.0)
Requires-Dist: packaging (>=24.2,<25.0)
Requires-Dist: pandas (>=2.1.2,<3.0.0)
Requires-Dist: pyarrow (>=18.0.0,<19.0.0)
Requires-Dist: pysam (>=0.23.0,<0.24.0)
Project-URL: Repository, https://github.com/metagenopolis/meteor
